{
  "__inputs": [
    {
      "name": "DS_HOSTNAMES",
      "label": "hostnames",
      "description": "",
      "type": "datasource",
      "pluginId": "influxdb",
      "pluginName": "InfluxDB"
    },
    {
      "name": "DS_USERNAME",
      "label": "username",
      "description": "",
      "type": "datasource",
      "pluginId": "influxdb",
      "pluginName": "InfluxDB"
    },
    {
      "name": "DS_INTERFACE_BW",
      "label": "interface_bw",
      "description": "",
      "type": "datasource",
      "pluginId": "influxdb",
      "pluginName": "InfluxDB"
    },
    {
      "name": "DS_INTERFACE_DROPS",
      "label": "interface_drops",
      "description": "",
      "type": "datasource",
      "pluginId": "influxdb",
      "pluginName": "InfluxDB"
    }
  ],
  "__requires": [
    {
      "type": "grafana",
      "id": "grafana",
      "name": "Grafana",
      "version": "6.6.2"
    },
    {
      "type": "panel",
      "id": "graph",
      "name": "Graph",
      "version": ""
    },
    {
      "type": "datasource",
      "id": "influxdb",
      "name": "InfluxDB",
      "version": "1.0.0"
    },
    {
      "type": "panel",
      "id": "table",
      "name": "Table",
      "version": ""
    }
  ],
  "annotations": {
    "list": [
      {
        "builtIn": 1,
        "datasource": "-- Grafana --",
        "enable": true,
        "hide": true,
        "iconColor": "rgba(0, 211, 255, 1)",
        "name": "Annotations & Alerts",
        "type": "dashboard"
      }
    ]
  },
  "editable": true,
  "gnetId": null,
  "graphTooltip": 0,
  "id": null,
  "links": [],
  "panels": [
    {
      "columns": [],
      "datasource": "${DS_HOSTNAMES}",
      "fontSize": "100%",
      "gridPos": {
        "h": 9,
        "w": 12,
        "x": 0,
        "y": 0
      },
      "id": 4,
      "options": {},
      "pageSize": null,
      "showHeader": true,
      "sort": {
        "col": 0,
        "desc": true
      },
      "styles": [
        {
          "alias": "Time",
          "align": "auto",
          "dateFormat": "YYYY-MM-DD HH:mm:ss",
          "pattern": "Time",
          "type": "date"
        },
        {
          "alias": "",
          "align": "right",
          "colorMode": null,
          "colors": [
            "rgba(245, 54, 54, 0.9)",
            "rgba(237, 129, 40, 0.89)",
            "rgba(50, 172, 45, 0.97)"
          ],
          "decimals": 2,
          "pattern": "/.*/",
          "thresholds": [],
          "type": "number",
          "unit": "short"
        }
      ],
      "targets": [
        {
          "groupBy": [
            {
              "params": [
                "device-model"
              ],
              "type": "tag"
            },
            {
              "params": [
                "host-name"
              ],
              "type": "tag"
            },
            {
              "params": [
                "site-id"
              ],
              "type": "tag"
            },
            {
              "params": [
                "system-ip"
              ],
              "type": "tag"
            }
          ],
          "measurement": "monitor",
          "orderByTime": "ASC",
          "policy": "default",
          "refId": "A",
          "resultFormat": "table",
          "select": [
            [
              {
                "params": [
                  "status"
                ],
                "type": "field"
              }
            ]
          ],
          "tags": []
        }
      ],
      "timeFrom": null,
      "timeShift": null,
      "title": "Hostnames",
      "transform": "table",
      "type": "table"
    },
    {
      "columns": [],
      "datasource": "${DS_USERNAME}",
      "fontSize": "100%",
      "gridPos": {
        "h": 9,
        "w": 12,
        "x": 12,
        "y": 0
      },
      "id": 2,
      "options": {},
      "pageSize": null,
      "pluginVersion": "6.6.2",
      "showHeader": true,
      "sort": {
        "col": 0,
        "desc": true
      },
      "styles": [
        {
          "alias": "Time",
          "align": "auto",
          "dateFormat": "YYYY-MM-DD HH:mm:ss",
          "pattern": "Time",
          "type": "date"
        },
        {
          "alias": "",
          "align": "right",
          "colorMode": null,
          "colors": [
            "rgba(245, 54, 54, 0.9)",
            "rgba(237, 129, 40, 0.89)",
            "rgba(50, 172, 45, 0.97)"
          ],
          "decimals": 2,
          "pattern": "/.*/",
          "thresholds": [],
          "type": "number",
          "unit": "short"
        }
      ],
      "targets": [
        {
          "groupBy": [
            {
              "params": [
                "username"
              ],
              "type": "tag"
            }
          ],
          "measurement": "usernames",
          "orderByTime": "ASC",
          "policy": "default",
          "refId": "A",
          "resultFormat": "table",
          "select": [
            [
              {
                "params": [
                  "fullname"
                ],
                "type": "field"
              }
            ],
            [
              {
                "params": [
                  "group"
                ],
                "type": "field"
              }
            ]
          ],
          "tags": []
        }
      ],
      "timeFrom": null,
      "timeShift": null,
      "title": "Usernames",
      "transform": "table",
      "type": "table"
    },
    {
      "aliasColors": {},
      "bars": false,
      "dashLength": 10,
      "dashes": false,
      "datasource": "${DS_INTERFACE_BW}",
      "fill": 1,
      "fillGradient": 0,
      "gridPos": {
        "h": 8,
        "w": 12,
        "x": 0,
        "y": 9
      },
      "hiddenSeries": false,
      "id": 6,
      "interval": "",
      "legend": {
        "alignAsTable": false,
        "avg": false,
        "current": false,
        "max": false,
        "min": false,
        "show": true,
        "total": false,
        "values": false
      },
      "lines": true,
      "linewidth": 1,
      "nullPointMode": "null",
      "options": {
        "dataLinks": []
      },
      "percentage": false,
      "pointradius": 2,
      "points": false,
      "renderer": "flot",
      "seriesOverrides": [],
      "spaceLength": 10,
      "stack": false,
      "steppedLine": false,
      "targets": [
        {
          "alias": "$tag_interface",
          "groupBy": [
            {
              "params": [
                "interface"
              ],
              "type": "tag"
            }
          ],
          "measurement": "aggregation",
          "orderByTime": "ASC",
          "policy": "default",
          "refId": "A",
          "resultFormat": "time_series",
          "select": [
            [
              {
                "params": [
                  "tx_pkts"
                ],
                "type": "field"
              }
            ]
          ],
          "tags": []
        }
      ],
      "thresholds": [],
      "timeFrom": null,
      "timeRegions": [],
      "timeShift": null,
      "title": "TX Interface Bandwidth",
      "tooltip": {
        "shared": true,
        "sort": 0,
        "value_type": "individual"
      },
      "type": "graph",
      "xaxis": {
        "buckets": null,
        "mode": "time",
        "name": null,
        "show": true,
        "values": []
      },
      "yaxes": [
        {
          "format": "short",
          "label": null,
          "logBase": 1,
          "max": null,
          "min": null,
          "show": true
        },
        {
          "format": "short",
          "label": null,
          "logBase": 1,
          "max": null,
          "min": null,
          "show": true
        }
      ],
      "yaxis": {
        "align": false,
        "alignLevel": null
      }
    },
    {
      "aliasColors": {},
      "bars": false,
      "dashLength": 10,
      "dashes": false,
      "datasource": "${DS_INTERFACE_BW}",
      "fill": 1,
      "fillGradient": 0,
      "gridPos": {
        "h": 8,
        "w": 12,
        "x": 12,
        "y": 9
      },
      "hiddenSeries": false,
      "id": 9,
      "interval": "",
      "legend": {
        "alignAsTable": false,
        "avg": false,
        "current": false,
        "max": false,
        "min": false,
        "show": true,
        "total": false,
        "values": false
      },
      "lines": true,
      "linewidth": 1,
      "nullPointMode": "null",
      "options": {
        "dataLinks": []
      },
      "percentage": false,
      "pointradius": 2,
      "points": false,
      "renderer": "flot",
      "seriesOverrides": [],
      "spaceLength": 10,
      "stack": false,
      "steppedLine": false,
      "targets": [
        {
          "alias": "$tag_interface",
          "groupBy": [
            {
              "params": [
                "interface"
              ],
              "type": "tag"
            }
          ],
          "measurement": "aggregation",
          "orderByTime": "ASC",
          "policy": "default",
          "refId": "A",
          "resultFormat": "time_series",
          "select": [
            [
              {
                "params": [
                  "rx_pkts"
                ],
                "type": "field"
              }
            ]
          ],
          "tags": []
        }
      ],
      "thresholds": [],
      "timeFrom": null,
      "timeRegions": [],
      "timeShift": null,
      "title": "RX Interface Bandwidth",
      "tooltip": {
        "shared": true,
        "sort": 0,
        "value_type": "individual"
      },
      "type": "graph",
      "xaxis": {
        "buckets": null,
        "mode": "time",
        "name": null,
        "show": true,
        "values": []
      },
      "yaxes": [
        {
          "format": "short",
          "label": null,
          "logBase": 1,
          "max": null,
          "min": null,
          "show": true
        },
        {
          "format": "short",
          "label": null,
          "logBase": 1,
          "max": null,
          "min": null,
          "show": true
        }
      ],
      "yaxis": {
        "align": false,
        "alignLevel": null
      }
    },
    {
      "aliasColors": {},
      "bars": false,
      "cacheTimeout": null,
      "dashLength": 10,
      "dashes": false,
      "datasource": "${DS_INTERFACE_DROPS}",
      "fill": 1,
      "fillGradient": 5,
      "gridPos": {
        "h": 8,
        "w": 12,
        "x": 0,
        "y": 17
      },
      "hiddenSeries": false,
      "id": 10,
      "interval": "",
      "legend": {
        "avg": false,
        "current": false,
        "max": false,
        "min": false,
        "show": true,
        "total": false,
        "values": false
      },
      "lines": true,
      "linewidth": 1,
      "links": [],
      "nullPointMode": "null",
      "options": {
        "dataLinks": []
      },
      "percentage": false,
      "pluginVersion": "6.6.2",
      "pointradius": 2,
      "points": false,
      "renderer": "flot",
      "seriesOverrides": [],
      "spaceLength": 10,
      "stack": false,
      "steppedLine": true,
      "targets": [
        {
          "alias": "$tag_interface",
          "groupBy": [
            {
              "params": [
                "interface"
              ],
              "type": "tag"
            }
          ],
          "measurement": "aggregation",
          "orderByTime": "ASC",
          "policy": "default",
          "refId": "A",
          "resultFormat": "time_series",
          "select": [
            [
              {
                "params": [
                  "tx_drops"
                ],
                "type": "field"
              }
            ]
          ],
          "tags": []
        }
      ],
      "thresholds": [],
      "timeFrom": null,
      "timeRegions": [],
      "timeShift": null,
      "title": "TX Interface Drops",
      "tooltip": {
        "shared": true,
        "sort": 0,
        "value_type": "individual"
      },
      "type": "graph",
      "xaxis": {
        "buckets": null,
        "mode": "time",
        "name": null,
        "show": true,
        "values": []
      },
      "yaxes": [
        {
          "format": "short",
          "label": null,
          "logBase": 1,
          "max": null,
          "min": null,
          "show": true
        },
        {
          "format": "short",
          "label": null,
          "logBase": 1,
          "max": null,
          "min": null,
          "show": true
        }
      ],
      "yaxis": {
        "align": false,
        "alignLevel": null
      }
    },
    {
      "aliasColors": {},
      "bars": false,
      "cacheTimeout": null,
      "dashLength": 10,
      "dashes": false,
      "datasource": "${DS_INTERFACE_DROPS}",
      "fill": 1,
      "fillGradient": 5,
      "gridPos": {
        "h": 8,
        "w": 12,
        "x": 12,
        "y": 17
      },
      "hiddenSeries": false,
      "id": 8,
      "interval": "",
      "legend": {
        "avg": false,
        "current": false,
        "max": false,
        "min": false,
        "show": true,
        "total": false,
        "values": false
      },
      "lines": true,
      "linewidth": 1,
      "links": [],
      "nullPointMode": "null",
      "options": {
        "dataLinks": []
      },
      "percentage": false,
      "pluginVersion": "6.6.2",
      "pointradius": 2,
      "points": false,
      "renderer": "flot",
      "seriesOverrides": [],
      "spaceLength": 10,
      "stack": false,
      "steppedLine": true,
      "targets": [
        {
          "alias": "$tag_interface",
          "groupBy": [
            {
              "params": [
                "interface"
              ],
              "type": "tag"
            }
          ],
          "measurement": "aggregation",
          "orderByTime": "ASC",
          "policy": "default",
          "refId": "A",
          "resultFormat": "time_series",
          "select": [
            [
              {
                "params": [
                  "rx_drops"
                ],
                "type": "field"
              }
            ]
          ],
          "tags": []
        }
      ],
      "thresholds": [],
      "timeFrom": null,
      "timeRegions": [],
      "timeShift": null,
      "title": "RX Interface Drops",
      "tooltip": {
        "shared": true,
        "sort": 0,
        "value_type": "individual"
      },
      "type": "graph",
      "xaxis": {
        "buckets": null,
        "mode": "time",
        "name": null,
        "show": true,
        "values": []
      },
      "yaxes": [
        {
          "format": "short",
          "label": null,
          "logBase": 1,
          "max": null,
          "min": null,
          "show": true
        },
        {
          "format": "short",
          "label": null,
          "logBase": 1,
          "max": null,
          "min": null,
          "show": true
        }
      ],
      "yaxis": {
        "align": false,
        "alignLevel": null
      }
    }
  ],
  "schemaVersion": 22,
  "style": "dark",
  "tags": [],
  "templating": {
    "list": []
  },
  "time": {
    "from": "now-6h",
    "to": "now"
  },
  "timepicker": {
    "refresh_intervals": [
      "5s",
      "10s",
      "30s",
      "1m",
      "5m",
      "15m",
      "30m",
      "1h",
      "2h",
      "1d"
    ]
  },
  "timezone": "",
  "title": "Day2_Dashboard",
  "uid": "8G9qMi_Zz",
  "version": 19
}